CHANGES.txt
LICENSE.txt
MANIFEST.in
README.md
setup.py
GeobricksMODIS.egg-info/PKG-INFO
GeobricksMODIS.egg-info/SOURCES.txt
GeobricksMODIS.egg-info/dependency_links.txt
GeobricksMODIS.egg-info/requires.txt
GeobricksMODIS.egg-info/top_level.txt
geobricks_modis/__init__.py
geobricks_modis/__init__.pyc
geobricks_modis/config/__init__.py
geobricks_modis/config/__init__.pyc
geobricks_modis/config/gaul2modis.py
geobricks_modis/config/gaul2modis.pyc
geobricks_modis/config/modis_config.py
geobricks_modis/config/modis_config.pyc
geobricks_modis/core/__init__.py
geobricks_modis/core/__init__.pyc
geobricks_modis/core/modis_core.py
geobricks_modis/core/modis_core.pyc
geobricks_modis/rest/__init__.py
geobricks_modis/rest/__init__.pyc
geobricks_modis/rest/modis_rest.py
geobricks_modis/rest/modis_rest.pyc