Metadata-Version: 1.0
Name: GeobricksMODIS
Version: 0.1.5
Summary: MODIS plug-in for Geobricks downloader.
Home-page: http://pypi.python.org/pypi/GeobricksMODIS/
Author: Simone Murzilli; Guido Barbaglia
Author-email: geobrickspy@gmail.com
License: LICENSE.txt
Platform: UNKNOWN
